LICENSE
MANIFEST.in
README.md
requirements.txt
setup.cfg
setup.py
zk-flock
distributedflock/Zookeeper.py
distributedflock/__init__.py
distributedflock/pdeathsig.py
distributedflock/ZKeeperAPI/__init__.py
distributedflock/ZKeeperAPI/zkapi.py
tests/requirements.txt
zk_flock.egg-info/PKG-INFO
zk_flock.egg-info/SOURCES.txt
zk_flock.egg-info/dependency_links.txt
zk_flock.egg-info/not-zip-safe
zk_flock.egg-info/requires.txt
zk_flock.egg-info/top_level.txt