Metadata-Version: 1.1
Name: zk-flock
Version: 0.1.4.1
Summary: Utility to launch process under distributed Zookeeper lock
Home-page: https://github.com/noxiouz/python-flock
Author: Anton Tiurin
Author-email: noxiouz@yandex.ru
License:                    GNU LESSER GENERAL PUBLIC LICENSE
